sobe/__init__.py
sobe/aws.py
sobe/config.py
sobe/main.py
sobe-0.4.1.dist-info/WHEEL
sobe-0.4.1.dist-info/entry_points.txt
sobe-0.4.1.dist-info/METADATA
sobe-0.4.1.dist-info/RECORD
