Metadata-Version: 2.4
Name: sobe
Version: 0.4.1
Summary: AWS-based drop box uploader
Author: Liz Balbuena
License-Expression: MIT
Classifier: Development Status :: 5 - Production/Stable
Classifier: Environment :: Console
Classifier: License :: OSI Approved :: MIT License
Classifier: Operating System :: OS Independent
Classifier: Programming Language :: Python
Classifier: Programming Language :: Python :: 3.11
Classifier: Programming Language :: Python :: 3.12
Classifier: Programming Language :: Python :: 3.13
Classifier: Topic :: Communications :: File Sharing
Classifier: Topic :: Utilities
Requires-Dist: boto3>=1.40.49
Requires-Dist: platformdirs>=4.5.0
Requires-Dist: puremagic>=1.30
Requires-Dist: furo>=2024.8.6 ; extra == 'docs'
Requires-Dist: sphinx>=7.0.0 ; extra == 'docs'
Requires-Dist: sphinx-autodoc-typehints>=2.0.0 ; extra == 'docs'
Requires-Python: >=3.11
Project-URL: Changelog, https://github.com/Liz4v/sobe/releases
Project-URL: Documentation, https://github.com/Liz4v/sobe/blob/main/README.md
Project-URL: Homepage, https://github.com/Liz4v/sobe
Project-URL: Issues, https://github.com/Liz4v/sobe/issues
Project-URL: Repository, https://github.com/Liz4v/sobe.git
Provides-Extra: docs
